tensorflow_graphics/LICENSE
tensorflow_graphics/__init__.py
tensorflow_graphics/opensource_only.files
tensorflow_graphics/datasets/__init__.py
tensorflow_graphics/datasets/features/__init__.py
tensorflow_graphics/datasets/features/camera_feature.py
tensorflow_graphics/datasets/features/camera_feature_test.py
tensorflow_graphics/datasets/features/pose_feature.py
tensorflow_graphics/datasets/features/pose_feature_test.py
tensorflow_graphics/datasets/features/trimesh_feature.py
tensorflow_graphics/datasets/features/trimesh_feature_test.py
tensorflow_graphics/datasets/features/voxel_feature.py
tensorflow_graphics/datasets/features/voxel_feature_test.py
tensorflow_graphics/datasets/features/test_data/cube.mat
tensorflow_graphics/datasets/features/test_data/cube.obj
tensorflow_graphics/datasets/modelnet40/__init__.py
tensorflow_graphics/datasets/modelnet40/checksums.tsv
tensorflow_graphics/datasets/modelnet40/modelnet40.py
tensorflow_graphics/datasets/modelnet40/modelnet40_checksums.py
tensorflow_graphics/datasets/modelnet40/modelnet40_makefakes.py
tensorflow_graphics/datasets/modelnet40/modelnet40_run.py
tensorflow_graphics/datasets/modelnet40/modelnet40_show.py
tensorflow_graphics/datasets/modelnet40/modelnet40_test.py
tensorflow_graphics/datasets/modelnet40/fakes/modelnet40_ply_hdf5_2048/ply_data_test0.h5
tensorflow_graphics/datasets/modelnet40/fakes/modelnet40_ply_hdf5_2048/ply_data_test1.h5
tensorflow_graphics/datasets/modelnet40/fakes/modelnet40_ply_hdf5_2048/ply_data_train0.h5
tensorflow_graphics/datasets/modelnet40/fakes/modelnet40_ply_hdf5_2048/ply_data_train1.h5
tensorflow_graphics/datasets/modelnet40/fakes/modelnet40_ply_hdf5_2048/ply_data_train2.h5
tensorflow_graphics/datasets/modelnet40/fakes/modelnet40_ply_hdf5_2048/test_files.txt
tensorflow_graphics/datasets/modelnet40/fakes/modelnet40_ply_hdf5_2048/train_files.txt
tensorflow_graphics/datasets/pix3d/__init__.py
tensorflow_graphics/datasets/pix3d/checksums.tsv
tensorflow_graphics/datasets/pix3d/pix3d.py
tensorflow_graphics-2021.12.3.dist-info/LICENSE
tensorflow_graphics-2021.12.3.dist-info/METADATA
tensorflow_graphics-2021.12.3.dist-info/WHEEL
tensorflow_graphics-2021.12.3.dist-info/top_level.txt
tensorflow_graphics-2021.12.3.dist-info/RECORD
